pyfuncs/__init__.py
pyfuncs/chrome_cookie.py
pyfuncs-0.0.4.dist-info/LICENSE
pyfuncs-0.0.4.dist-info/METADATA
pyfuncs-0.0.4.dist-info/WHEEL
pyfuncs-0.0.4.dist-info/top_level.txt
pyfuncs-0.0.4.dist-info/RECORD
