Metadata-Version: 2.1
Name: pyfuncs
Version: 0.0.4
Summary: common methods
Home-page: https://github.com/fishs-x/pyfuncs
Author: zhangzhch
Author-email: zhangzhch2013@foxmail.com
License: UNKNOWN
Platform: UNKNOWN
Classifier: Programming Language :: Python :: 3
Classifier: License :: OSI Approved :: MIT License
Classifier: Operating System :: OS Independent
Requires-Python: >=3.6
Requires-Dist: cryptography
Requires-Dist: keyring
